Metadata-Version: 2.1
Name: AFEM
Version: 1.0.34
Summary: A Finite Element Python implementation
Home-page: https://github.com/ZibraMax/FEM
Author: Arturo Rodriguez
Author-email: da.rodriguezh@uniandes.edu.com
Requires-Python: >=3.6
License-File: LICENSE
Requires-Dist: numpy
Requires-Dist: matplotlib
Requires-Dist: triangle
Requires-Dist: scipy
Requires-Dist: tqdm
Provides-Extra: docs
Requires-Dist: sphinx ; extra == 'docs'
Requires-Dist: m2r2 ; extra == 'docs'
Requires-Dist: docutils (==0.18) ; extra == 'docs'
Requires-Dist: furo ; extra == 'docs'
Provides-Extra: test
Requires-Dist: pytest ; extra == 'test'
Requires-Dist: pytest-emoji ; extra == 'test'
